dynbike_functions/.ipynb_checkpoints/__init__-checkpoint.py
dynbike_functions/.ipynb_checkpoints/checkers-checkpoint.py
dynbike_functions/.ipynb_checkpoints/helpers-checkpoint.py
dynbike_functions/.ipynb_checkpoints/plotters-checkpoint.py
dynbike_functions/.ipynb_checkpoints/requirements-checkpoint.txt
dynbike_functions/.ipynb_checkpoints/stats_functions-checkpoint.py
dynbike_functions/__init__.py
dynbike_functions/checkers.py
dynbike_functions/helpers.py
dynbike_functions/plotters.py
dynbike_functions/requirements.txt
dynbike_functions/stats_functions.py
dynbike_functions-0.1.4.dist-info/LICENSE
dynbike_functions-0.1.4.dist-info/WHEEL
dynbike_functions-0.1.4.dist-info/METADATA
dynbike_functions-0.1.4.dist-info/RECORD
